fanix_editor_frwk/__init__.py
fanix_editor_frwk/data.py
fanix_editor_frwk/debug.py
fanix_editor_frwk/diff.py
fanix_editor_frwk/view.py
fanix_editor_frwk/widget.py
fanix_editor_frwk-0.0.1.dist-info/licenses/LICENSE
fanix_editor_frwk-0.0.1.dist-info/METADATA
fanix_editor_frwk-0.0.1.dist-info/WHEEL
fanix_editor_frwk-0.0.1.dist-info/top_level.txt
fanix_editor_frwk-0.0.1.dist-info/RECORD
