Metadata-Version: 2.4
Name: fanix-editor-frwk
Version: 0.0.1
Summary: A editor framework based on immutable data structures
Author-email: Fan Yang <fanyangrocks@qq.com>
Project-URL: Homepage, https://github.com/fanyangrocks/fanix-editor-frwk
Requires-Python: >=3.12
License-File: LICENSE
Requires-Dist: pyrsistent==0.20.0
Requires-Dist: PySide6==6.9.1
Dynamic: license-file
